{
  "updated_at": "2026-03-07T17:20:57.261388Z",
  "template_count": 10,
  "by_domain": {
    "3d_vision": [
      {
        "id": "TPL-3D-A",
        "name": "3D Vision · Decomposition Variant",
        "domain": "3d_vision",
        "variant": "A",
        "strategy": "pipeline_reframing",
        "schema_version": "template.intro.v3",
        "intro_paragraphs": 7,
        "paragraph_cards": 7,
        "reorder_profiles": 3
      },
      {
        "id": "TPL-3D-B",
        "name": "3D Vision · Efficiency-Accuracy Variant",
        "domain": "3d_vision",
        "variant": "B",
        "strategy": "tradeoff_bridge",
        "schema_version": "template.intro.v3",
        "intro_paragraphs": 7,
        "paragraph_cards": 7,
        "reorder_profiles": 3
      }
    ],
    "benchmark_task": [
      {
        "id": "TPL-BENCH-A",
        "name": "Task/Benchmark · Data-Governance Variant",
        "domain": "benchmark_task",
        "variant": "A",
        "strategy": "task_benchmark_definition",
        "schema_version": "template.intro.v3",
        "intro_paragraphs": 6,
        "paragraph_cards": 6,
        "reorder_profiles": 3
      },
      {
        "id": "TPL-BENCH-B",
        "name": "Task/Benchmark · Protocol-Driven Variant",
        "domain": "benchmark_task",
        "variant": "B",
        "strategy": "theory_formalization",
        "schema_version": "template.intro.v3",
        "intro_paragraphs": 5,
        "paragraph_cards": 5,
        "reorder_profiles": 3
      }
    ],
    "medical_imaging": [
      {
        "id": "TPL-MED-A",
        "name": "Medical CV · Evidence-Risk Balanced Variant",
        "domain": "medical_imaging",
        "variant": "A",
        "strategy": "tradeoff_bridge",
        "schema_version": "template.intro.v3",
        "intro_paragraphs": 6,
        "paragraph_cards": 6,
        "reorder_profiles": 3
      }
    ],
    "seg_track": [
      {
        "id": "TPL-SEG-A",
        "name": "Segmentation/Tracking · Failure-Taxonomy Variant",
        "domain": "seg_track",
        "variant": "A",
        "strategy": "pipeline_reframing",
        "schema_version": "template.intro.v3",
        "intro_paragraphs": 7,
        "paragraph_cards": 7,
        "reorder_profiles": 3
      },
      {
        "id": "TPL-SEG-B",
        "name": "Segmentation/Tracking · End-to-End Variant",
        "domain": "seg_track",
        "variant": "B",
        "strategy": "efficiency_first",
        "schema_version": "template.intro.v3",
        "intro_paragraphs": 7,
        "paragraph_cards": 7,
        "reorder_profiles": 3
      }
    ],
    "efficiency_system": [
      {
        "id": "TPL-TH-A",
        "name": "Theory/Optimization · Condition-Result-Regime Variant",
        "domain": "efficiency_system",
        "variant": "A",
        "strategy": "theory_formalization",
        "schema_version": "template.intro.v3",
        "intro_paragraphs": 6,
        "paragraph_cards": 6,
        "reorder_profiles": 3
      }
    ],
    "vlm_multimodal": [
      {
        "id": "TPL-VLM-A",
        "name": "VLM/MMLM · Tradeoff-Grounded Variant",
        "domain": "vlm_multimodal",
        "variant": "A",
        "strategy": "tradeoff_bridge",
        "schema_version": "template.intro.v3",
        "intro_paragraphs": 7,
        "paragraph_cards": 7,
        "reorder_profiles": 3
      },
      {
        "id": "TPL-VLM-B",
        "name": "VLM/MMLM · Benchmark-Protocol Variant",
        "domain": "vlm_multimodal",
        "variant": "B",
        "strategy": "task_benchmark_definition",
        "schema_version": "template.intro.v3",
        "intro_paragraphs": 6,
        "paragraph_cards": 6,
        "reorder_profiles": 3
      }
    ]
  }
}